dbpa/__init__.py
dbpa/cli.py
dbpa/py.typed
dbpa/config/config_schema.py
dbpa/core/__init__.py
dbpa/core/config_loader.py
dbpa/database/__init__.py
dbpa/database/database_connection.py
dbpa/database/table_manager.py
dbpa/models/__init__.py
dbpa/models/config.py
dbpa/streamlit/__init__.py
dbpa/streamlit/app.py
dbpa/streamlit/pages/query_history.py
dbpa/streamlit/pages/settings.py
dbpa/streamlit/pages/table_details.py
dbpa/txt2sql/agents.py
dbpa/txt2sql/engine.py
dbpa/txt2sql/multilingual.py
dbpa/txt2sql/vector_store.py
dbpa/txt2sql/agents/__init__.py
dbpa/txt2sql/agents/base.py
dbpa/txt2sql/agents/data_management_agent.py
dbpa/txt2sql/agents/schema_analysis.py
dbpa/txt2sql/agents/training_agent.py
dbpa/txt2sql/agents/schema/__init__.py
dbpa/txt2sql/agents/schema/analyzer.py
dbpa/txt2sql/agents/schema/template_generator.py
dbpa/txt2sql/agents/schema/utils.py
dbpa/txt2sql/models/__init__.py
dbpa/txt2sql/models/agent_models.py
dbpa/txt2sql/models/examples.py
dbpa/txt2sql/vector_store/__init__.py
dbpa/txt2sql/vector_store/store.py
dbpa/ui/__init__.py
dbpa/ui/components/__init__.py
dbpa/ui/components/vector_store_manager.py
dbpa/ui/pages/__init__.py
dbpa/ui/pages/configuration.py
dbpa/ui/pages/vector_store.py
dbpa/utils/__init__.py
dbpa/utils/error_logger.py
dbpa-0.2.0.dist-info/LICENSE
dbpa-0.2.0.dist-info/METADATA
dbpa-0.2.0.dist-info/WHEEL
dbpa-0.2.0.dist-info/top_level.txt
dbpa-0.2.0.dist-info/RECORD
