Metadata-Version: 2.2
Name: dbpa
Version: 0.2.0
Summary: Database Personal Assistant - An AI-powered database management system with advanced text-to-SQL capabilities
Home-page: https://github.com/achimdehnert/dbpa
Author: Achim Dehnert
Author-email: Achim Dehnert <achim@example.com>
License: MIT
Project-URL: Homepage, https://github.com/achimdehnert/dbpa
Project-URL: Documentation, https://github.com/achimdehnert/dbpa/docs
Project-URL: Repository, https://github.com/achimdehnert/dbpa.git
Project-URL: Issues, https://github.com/achimdehnert/dbpa/issues
Keywords: database,sql,ai,nlp,text-to-sql,schema-analysis
Classifier: Development Status :: 4 - Beta
Classifier: Intended Audience :: Developers
Classifier: License :: OSI Approved :: MIT License
Classifier: Programming Language :: Python :: 3
Classifier: Programming Language :: Python :: 3.8
Classifier: Programming Language :: Python :: 3.9
Classifier: Programming Language :: Python :: 3.10
Classifier: Programming Language :: Python :: 3.11
Classifier: Topic :: Database
Classifier: Topic :: Software Development :: Libraries :: Python Modules
Classifier: Topic :: Scientific/Engineering :: Artificial Intelligence
Requires-Python: >=3.8
License-File: LICENSE
Requires-Dist: sqlalchemy>=1.4.0
Requires-Dist: sentence-transformers>=2.3.1
Requires-Dist: faiss-cpu>=1.7.4
Requires-Dist: pydantic>=2.6.1
Requires-Dist: streamlit>=1.32.0
Requires-Dist: torch>=2.0.0
Requires-Dist: typing-extensions>=4.0.0
Provides-Extra: dev
Requires-Dist: pytest>=6.0; extra == "dev"
Requires-Dist: pytest-cov>=2.0; extra == "dev"
Requires-Dist: black>=22.0; extra == "dev"
Requires-Dist: isort>=5.0; extra == "dev"
Requires-Dist: mypy>=0.900; extra == "dev"
Requires-Dist: ruff>=0.0.1; extra == "dev"
Requires-Dist: robotframework>=6.0; extra == "dev"
Dynamic: author
Dynamic: home-page
Dynamic: requires-python
